LICENSE
README.md
setup.py
dashpro.egg-info/PKG-INFO
dashpro.egg-info/SOURCES.txt
dashpro.egg-info/dependency_links.txt
dashpro.egg-info/requires.txt
dashpro.egg-info/top_level.txt
migrations/0001_initial.py
migrations/__init__.py
registry/__init__.py
registry/model_registry.py
registry/url_registry.py
render/__init__.py
templatetags/__init__.py
templatetags/dp_rendering_utils.py
utils/__init__.py
views/__init__.py
views/createView.py
views/deleteView.py
views/detailView.py
views/listView.py
views/updateView.py