Metadata-Version: 2.1
Name: dashpro
Version: 0.2
Summary: A dynamic Django dashboard 
Home-page: https://github.com/ehusseinnaim/Dashpro.git
Author: Hussein Naim
Author-email: ehusseinnaim@gmail.com
Classifier: Development Status :: 3 - Alpha
Classifier: Framework :: Django
Classifier: Intended Audience :: Developers
Classifier: License :: OSI Approved :: MIT License
Classifier: Programming Language :: Python :: 3
Classifier: Programming Language :: Python :: 3.6
Classifier: Programming Language :: Python :: 3.7
Classifier: Programming Language :: Python :: 3.8
Classifier: Programming Language :: Python :: 3.9
Classifier: Topic :: Software Development :: Libraries :: Application Frameworks
Classifier: Topic :: Software Development :: Libraries :: Python Modules
License-File: LICENSE
